LICENSE
MANIFEST.in
README.md
requirements.txt
setup.cfg
setup.py
cb/__init__.py
cb/cli.py
cb/commands.py
cb/log.py
cb/server.py
cb/tools.py
cb.egg-info/PKG-INFO
cb.egg-info/SOURCES.txt
cb.egg-info/dependency_links.txt
cb.egg-info/entry_points.txt
cb.egg-info/requires.txt
cb.egg-info/top_level.txt
cb/init_source/_config.yml
cb/init_source/hello.md
cb/themes/snow/atom.xml
cb/themes/snow/base.html
cb/themes/snow/index.html
cb/themes/snow/page.html
cb/themes/snow/static/css/style.css
cb/themes/snow/static/css/tango.css
cb/themes/yasimple/atom.xml
cb/themes/yasimple/base.html
cb/themes/yasimple/index.html
cb/themes/yasimple/page.html
cb/themes/yasimple/static/css/style.css
cb/themes/yasimple/static/css/tango.css
cb/themes/ywwhite/atom.xml
cb/themes/ywwhite/base.html
cb/themes/ywwhite/index.html
cb/themes/ywwhite/page.html
cb/themes/ywwhite/static/style.css