Metadata-Version: 1.0
Name: cb
Version: 1.0.7
Summary: Cb is a blog building tool inspired by tankywoo/simiki.
Home-page: https://github.com/wlwang41/cb
Author: crow
Author-email: wlwang41@gmail.com
License: MIT License
Keywords: blog,static page
Platform: UNKNOWN
